setup.py
distributions_edx6/Binomialdistribution.py
distributions_edx6/Gaussiandistribution.py
distributions_edx6/Generaldistribution.py
distributions_edx6/__init__.py
distributions_edx6.egg-info/PKG-INFO
distributions_edx6.egg-info/SOURCES.txt
distributions_edx6.egg-info/dependency_links.txt
distributions_edx6.egg-info/not-zip-safe
distributions_edx6.egg-info/top_level.txt